{"cameraMode":{"drawMode":0,"name":"Shaded","section":"Shading Mode"},"sceneLighting":true,"audioPlay":false,"sceneViewState":{"m_AlwaysRefresh":false,"showFog":true,"showSkybox":true,"showFlares":true,"showImageEffects":true,"showParticleSystems":true,"showVisualEffectGraphs":true,"m_FxEnabled":true},"in2DMode":false,"pivot":{"x":-3.0130581855773927,"y":-186.67823791503907,"z":19.937698364257814},"rotation":{"x":-0.6548082232475281,"y":-0.0361604318022728,"z":0.03137878328561783,"w":-0.7542956471443176},"size":132.8227081298828,"orthographic":false}